[
    {
        "id": 1,
        "nameChs": "门前清自摸和",
        "nameChsT": "門前清自摸和",
        "nameJp": "門前清自摸和",
        "nameEn": "Fully Concealed Hand",
        "nameKr": "멘젠쯔모",
        "xuanshang": 0,
        "yiman": 0,
        "fanMenqing": 1,
        "fanFulu": 1,
        "showIndex": 70,
        "sound": "fan_zimo",
        "isGuyi": 0,
        "rarity": 0,
        "showRange_1": "",
        "showRange_2": "",
        "mergeId": 0,
        "mark": 0
    },
    {
        "id": 2,
        "nameChs": "立直",
        "nameChsT": "立直",
        "nameJp": "立直",
        "nameEn": "Riichi",
        "nameKr": "리치",
        "xuanshang": 0,
        "yiman": 0,
        "fanMenqing": 1,
        "fanFulu": 1,
        "showIndex": 10,
        "sound": "fan_liqi",
        "isGuyi": 0,
        "rarity": 0,
        "showRange_1": "",
        "showRange_2": "",
        "mergeId": 0,
        "mark": 0
    },
    {
        "id": 3,
        "nameChs": "枪杠",
        "nameChsT": "槍槓",
        "nameJp": "槍槓",
        "nameEn": "Robbing a Kan",
        "nameKr": "창깡",
        "xuanshang": 0,
        "yiman": 0,
        "fanMenqing": 1,
        "fanFulu": 1,
        "showIndex": 30,
        "sound": "fan_qianggang",
        "isGuyi": 0,
        "rarity": 0,
        "showRange_1": "",
        "showRange_2": "",
        "mergeId": 0,
        "mark": 0
    },
    {
        "id": 4,
        "nameChs": "岭上开花",
        "nameChsT": "嶺上開花",
        "nameJp": "嶺上開花",
        "nameEn": "After a Kan",
        "nameKr": "영상개화",
        "xuanshang": 0,
        "yiman": 0,
        "fanMenqing": 1,
        "fanFulu": 1,
        "showIndex": 40,
        "sound": "fan_lingshang",
        "isGuyi": 0,
        "rarity": 0,
        "showRange_1": "",
        "showRange_2": "",
        "mergeId": 0,
        "mark": 0
    },
    {
        "id": 5,
        "nameChs": "海底摸月",
        "nameChsT": "海底摸月",
        "nameJp": "海底摸月",
        "nameEn": "Under the Sea",
        "nameKr": "해저로월",
        "xuanshang": 0,
        "yiman": 0,
        "fanMenqing": 1,
        "fanFulu": 1,
        "showIndex": 50,
        "sound": "fan_haidi",
        "isGuyi": 0,
        "rarity": 0,
        "showRange_1": "",
        "showRange_2": "",
        "mergeId": 0,
        "mark": 0
    },
    {
        "id": 6,
        "nameChs": "河底捞鱼",
        "nameChsT": "河底撈魚",
        "nameJp": "河底撈魚",
        "nameEn": "Under the River",
        "nameKr": "하저로어",
        "xuanshang": 0,
        "yiman": 0,
        "fanMenqing": 1,
        "fanFulu": 1,
        "showIndex": 60,
        "sound": "fan_hedi",
        "isGuyi": 0,
        "rarity": 0,
        "showRange_1": "",
        "showRange_2": "",
        "mergeId": 0,
        "mark": 0
    },
    {
        "id": 7,
        "nameChs": "役牌 白",
        "nameChsT": "役牌 白",
        "nameJp": "役牌 白",
        "nameEn": "White Dragon",
        "nameKr": "역패 백",
        "xuanshang": 0,
        "yiman": 0,
        "fanMenqing": 1,
        "fanFulu": 1,
        "showIndex": 120,
        "sound": "fan_bai",
        "isGuyi": 0,
        "rarity": 0,
        "showRange_1": "",
        "showRange_2": "",
        "mergeId": 0,
        "mark": 0
    },
    {
        "id": 8,
        "nameChs": "役牌 发",
        "nameChsT": "役牌 發",
        "nameJp": "役牌 發",
        "nameEn": "Green Dragon",
        "nameKr": "역패 발",
        "xuanshang": 0,
        "yiman": 0,
        "fanMenqing": 1,
        "fanFulu": 1,
        "showIndex": 130,
        "sound": "fan_fa",
        "isGuyi": 0,
        "rarity": 0,
        "showRange_1": "",
        "showRange_2": "",
        "mergeId": 0,
        "mark": 0
    },
    {
        "id": 9,
        "nameChs": "役牌 中",
        "nameChsT": "役牌 中",
        "nameJp": "役牌 中",
        "nameEn": "Red Dragon",
        "nameKr": "역패 중",
        "xuanshang": 0,
        "yiman": 0,
        "fanMenqing": 1,
        "fanFulu": 1,
        "showIndex": 140,
        "sound": "fan_zhong",
        "isGuyi": 0,
        "rarity": 0,
        "showRange_1": "",
        "showRange_2": "",
        "mergeId": 0,
        "mark": 0
    },
    {
        "id": 10,
        "nameChs": "役牌:门风牌",
        "nameChsT": "役牌：門風牌",
        "nameJp": "役牌:自風牌",
        "nameEn": "Seat Wind",
        "nameKr": "역패: 자풍패",
        "xuanshang": 0,
        "yiman": 0,
        "fanMenqing": 1,
        "fanFulu": 1,
        "showIndex": 150,
        "sound": "",
        "isGuyi": 0,
        "rarity": 0,
        "showRange_1": "",
        "showRange_2": "",
        "mergeId": 0,
        "mark": 0
    },
    {
        "id": 11,
        "nameChs": "役牌:场风牌",
        "nameChsT": "役牌：場風牌",
        "nameJp": "役牌:場風牌",
        "nameEn": "Prevalent Wind",
        "nameKr": "역패: 장풍패",
        "xuanshang": 0,
        "yiman": 0,
        "fanMenqing": 1,
        "fanFulu": 1,
        "showIndex": 160,
        "sound": "",
        "isGuyi": 0,
        "rarity": 0,
        "showRange_1": "",
        "showRange_2": "",
        "mergeId": 0,
        "mark": 0
    },
    {
        "id": 12,
        "nameChs": "断幺九",
        "nameChsT": "斷么九",
        "nameJp": "断幺九",
        "nameEn": "All Simples",
        "nameKr": "탕야오",
        "xuanshang": 0,
        "yiman": 0,
        "fanMenqing": 1,
        "fanFulu": 1,
        "showIndex": 170,
        "sound": "fan_duanyao",
        "isGuyi": 0,
        "rarity": 0,
        "showRange_1": "",
        "showRange_2": "",
        "mergeId": 0,
        "mark": 0
    },
    {
        "id": 13,
        "nameChs": "一杯口",
        "nameChsT": "一盃口",
        "nameJp": "一盃口",
        "nameEn": "Pure Double Sequence",
        "nameKr": "이페코",
        "xuanshang": 0,
        "yiman": 0,
        "fanMenqing": 1,
        "fanFulu": 0,
        "showIndex": 90,
        "sound": "fan_yibeikou",
        "isGuyi": 0,
        "rarity": 0,
        "showRange_1": "",
        "showRange_2": "",
        "mergeId": 0,
        "mark": 0
    },
    {
        "id": 14,
        "nameChs": "平和",
        "nameChsT": "平和",
        "nameJp": "平和",
        "nameEn": "Pinfu",
        "nameKr": "핑후",
        "xuanshang": 0,
        "yiman": 0,
        "fanMenqing": 1,
        "fanFulu": 0,
        "showIndex": 80,
        "sound": "fan_pinghu",
        "isGuyi": 0,
        "rarity": 0,
        "showRange_1": "",
        "showRange_2": "",
        "mergeId": 0,
        "mark": 0
    },
    {
        "id": 15,
        "nameChs": "混全带幺九",
        "nameChsT": "混全帶么九",
        "nameJp": "混全帯幺九",
        "nameEn": "Half Outside Hand",
        "nameKr": "찬타",
        "xuanshang": 0,
        "yiman": 0,
        "fanMenqing": 2,
        "fanFulu": 1,
        "showIndex": 180,
        "sound": "fan_hunquandaiyaojiu",
        "isGuyi": 0,
        "rarity": 0,
        "showRange_1": "",
        "showRange_2": "",
        "mergeId": 0,
        "mark": 0
    },
    {
        "id": 16,
        "nameChs": "一气通贯",
        "nameChsT": "一氣通貫",
        "nameJp": "一気通貫",
        "nameEn": "Pure Straight",
        "nameKr": "일기통관",
        "xuanshang": 0,
        "yiman": 0,
        "fanMenqing": 2,
        "fanFulu": 1,
        "showIndex": 190,
        "sound": "fan_yiqitongguan",
        "isGuyi": 0,
        "rarity": 0,
        "showRange_1": "",
        "showRange_2": "",
        "mergeId": 0,
        "mark": 0
    },
    {
        "id": 17,
        "nameChs": "三色同顺",
        "nameChsT": "三色同順",
        "nameJp": "三色同順",
        "nameEn": "Mixed Triple Sequence",
        "nameKr": "삼색동순",
        "xuanshang": 0,
        "yiman": 0,
        "fanMenqing": 2,
        "fanFulu": 1,
        "showIndex": 200,
        "sound": "fan_sansetongshun",
        "isGuyi": 0,
        "rarity": 0,
        "showRange_1": "1",
        "showRange_2": "",
        "mergeId": 0,
        "mark": 0
    },
    {
        "id": 18,
        "nameChs": "两立直",
        "nameChsT": "兩立直",
        "nameJp": "ダブル立直",
        "nameEn": "Double Riichi",
        "nameKr": "더블 리치",
        "xuanshang": 0,
        "yiman": 0,
        "fanMenqing": 2,
        "fanFulu": 2,
        "showIndex": 10,
        "sound": "fan_dliqi",
        "isGuyi": 0,
        "rarity": 0,
        "showRange_1": "",
        "showRange_2": "",
        "mergeId": 0,
        "mark": 0
    },
    {
        "id": 19,
        "nameChs": "三色同刻",
        "nameChsT": "三色同刻",
        "nameJp": "三色同刻",
        "nameEn": "Triple Triplets",
        "nameKr": "삼색동각",
        "xuanshang": 0,
        "yiman": 0,
        "fanMenqing": 2,
        "fanFulu": 2,
        "showIndex": 220,
        "sound": "fan_sansetongke",
        "isGuyi": 0,
        "rarity": 0,
        "showRange_1": "",
        "showRange_2": "",
        "mergeId": 0,
        "mark": 0
    },
    {
        "id": 20,
        "nameChs": "三杠子",
        "nameChsT": "三槓子",
        "nameJp": "三槓子",
        "nameEn": "Three Quads",
        "nameKr": "산깡쯔",
        "xuanshang": 0,
        "yiman": 0,
        "fanMenqing": 2,
        "fanFulu": 2,
        "showIndex": 230,
        "sound": "fan_sangangzi",
        "isGuyi": 0,
        "rarity": 0,
        "showRange_1": "",
        "showRange_2": "",
        "mergeId": 0,
        "mark": 0
    },
    {
        "id": 21,
        "nameChs": "对对和",
        "nameChsT": "對對和",
        "nameJp": "対々和",
        "nameEn": "All Triplets",
        "nameKr": "또이또이",
        "xuanshang": 0,
        "yiman": 0,
        "fanMenqing": 2,
        "fanFulu": 2,
        "showIndex": 240,
        "sound": "fan_duiduihu",
        "isGuyi": 0,
        "rarity": 0,
        "showRange_1": "",
        "showRange_2": "",
        "mergeId": 0,
        "mark": 0
    },
    {
        "id": 22,
        "nameChs": "三暗刻",
        "nameChsT": "三暗刻",
        "nameJp": "三暗刻",
        "nameEn": "Three Concealed Triplets",
        "nameKr": "산안커",
        "xuanshang": 0,
        "yiman": 0,
        "fanMenqing": 2,
        "fanFulu": 2,
        "showIndex": 250,
        "sound": "fan_sananke",
        "isGuyi": 0,
        "rarity": 0,
        "showRange_1": "",
        "showRange_2": "",
        "mergeId": 0,
        "mark": 0
    },
    {
        "id": 23,
        "nameChs": "小三元",
        "nameChsT": "小三元",
        "nameJp": "小三元",
        "nameEn": "Little Three Dragons",
        "nameKr": "소삼원",
        "xuanshang": 0,
        "yiman": 0,
        "fanMenqing": 2,
        "fanFulu": 2,
        "showIndex": 260,
        "sound": "fan_xiaosanyuan",
        "isGuyi": 0,
        "rarity": 0,
        "showRange_1": "",
        "showRange_2": "",
        "mergeId": 0,
        "mark": 0
    },
    {
        "id": 24,
        "nameChs": "混老头",
        "nameChsT": "混老頭",
        "nameJp": "混老頭",
        "nameEn": "All Terminals and Honors",
        "nameKr": "혼노두",
        "xuanshang": 0,
        "yiman": 0,
        "fanMenqing": 2,
        "fanFulu": 2,
        "showIndex": 270,
        "sound": "fan_hunlaotou",
        "isGuyi": 0,
        "rarity": 0,
        "showRange_1": "",
        "showRange_2": "",
        "mergeId": 0,
        "mark": 0
    },
    {
        "id": 25,
        "nameChs": "七对子",
        "nameChsT": "七對子",
        "nameJp": "七対子",
        "nameEn": "Seven Pairs",
        "nameKr": "치또이쯔",
        "xuanshang": 0,
        "yiman": 0,
        "fanMenqing": 2,
        "fanFulu": 2,
        "showIndex": 110,
        "sound": "fan_qiduizi",
        "isGuyi": 0,
        "rarity": 0,
        "showRange_1": "",
        "showRange_2": "",
        "mergeId": 0,
        "mark": 0
    },
    {
        "id": 26,
        "nameChs": "纯全带幺九",
        "nameChsT": "純全帶么九",
        "nameJp": "純全帯幺九",
        "nameEn": "Fully Outside Hand",
        "nameKr": "준찬타",
        "xuanshang": 0,
        "yiman": 0,
        "fanMenqing": 3,
        "fanFulu": 2,
        "showIndex": 280,
        "sound": "fan_chunquandaiyaojiu",
        "isGuyi": 0,
        "rarity": 0,
        "showRange_1": "",
        "showRange_2": "",
        "mergeId": 0,
        "mark": 0
    },
    {
        "id": 27,
        "nameChs": "混一色",
        "nameChsT": "混一色",
        "nameJp": "混一色",
        "nameEn": "Half Flush",
        "nameKr": "혼일색",
        "xuanshang": 0,
        "yiman": 0,
        "fanMenqing": 3,
        "fanFulu": 2,
        "showIndex": 290,
        "sound": "fan_hunyise",
        "isGuyi": 0,
        "rarity": 0,
        "showRange_1": "",
        "showRange_2": "",
        "mergeId": 0,
        "mark": 0
    },
    {
        "id": 28,
        "nameChs": "二杯口",
        "nameChsT": "二盃口",
        "nameJp": "二盃口",
        "nameEn": "Twice Pure Double Sequence",
        "nameKr": "량페코",
        "xuanshang": 0,
        "yiman": 0,
        "fanMenqing": 3,
        "fanFulu": 0,
        "showIndex": 100,
        "sound": "fan_erbeikou",
        "isGuyi": 0,
        "rarity": 0,
        "showRange_1": "",
        "showRange_2": "",
        "mergeId": 0,
        "mark": 0
    },
    {
        "id": 29,
        "nameChs": "清一色",
        "nameChsT": "清一色",
        "nameJp": "清一色",
        "nameEn": "Full Flush",
        "nameKr": "청일색",
        "xuanshang": 0,
        "yiman": 0,
        "fanMenqing": 6,
        "fanFulu": 5,
        "showIndex": 300,
        "sound": "fan_qingyise",
        "isGuyi": 0,
        "rarity": 0,
        "showRange_1": "",
        "showRange_2": "",
        "mergeId": 0,
        "mark": 0
    },
    {
        "id": 30,
        "nameChs": "一发",
        "nameChsT": "一發",
        "nameJp": "一発",
        "nameEn": "Ippatsu",
        "nameKr": "일발",
        "xuanshang": 1,
        "yiman": 0,
        "fanMenqing": 1,
        "fanFulu": 1,
        "showIndex": 20,
        "sound": "fan_yifa",
        "isGuyi": 0,
        "rarity": 0,
        "showRange_1": "",
        "showRange_2": "",
        "mergeId": 0,
        "mark": 0
    },
    {
        "id": 31,
        "nameChs": "宝牌",
        "nameChsT": "寶牌",
        "nameJp": "ドラ",
        "nameEn": "Dora",
        "nameKr": "도라",
        "xuanshang": 1,
        "yiman": 0,
        "fanMenqing": 1,
        "fanFulu": 1,
        "showIndex": 310,
        "sound": "",
        "isGuyi": 0,
        "rarity": 0,
        "showRange_1": "",
        "showRange_2": "",
        "mergeId": 0,
        "mark": 0
    },
    {
        "id": 32,
        "nameChs": "红宝牌",
        "nameChsT": "紅寶牌",
        "nameJp": "赤ドラ",
        "nameEn": "Red Five",
        "nameKr": "적도라",
        "xuanshang": 1,
        "yiman": 0,
        "fanMenqing": 1,
        "fanFulu": 1,
        "showIndex": 320,
        "sound": "",
        "isGuyi": 0,
        "rarity": 0,
        "showRange_1": "",
        "showRange_2": "",
        "mergeId": 0,
        "mark": 0
    },
    {
        "id": 33,
        "nameChs": "里宝牌",
        "nameChsT": "裡寶牌",
        "nameJp": "裏ドラ",
        "nameEn": "Ura Dora",
        "nameKr": "뒷도라",
        "xuanshang": 1,
        "yiman": 0,
        "fanMenqing": 1,
        "fanFulu": 1,
        "showIndex": 340,
        "sound": "",
        "isGuyi": 0,
        "rarity": 0,
        "showRange_1": "",
        "showRange_2": "",
        "mergeId": 0,
        "mark": 0
    },
    {
        "id": 34,
        "nameChs": "拔北宝牌",
        "nameChsT": "拔北寶牌",
        "nameJp": "抜きドラ",
        "nameEn": "Kita",
        "nameKr": "북도라",
        "xuanshang": 1,
        "yiman": 0,
        "fanMenqing": 1,
        "fanFulu": 1,
        "showIndex": 330,
        "sound": "",
        "isGuyi": 0,
        "rarity": 0,
        "showRange_1": "2",
        "showRange_2": "",
        "mergeId": 0,
        "mark": 0
    },
    {
        "id": 35,
        "nameChs": "天和",
        "nameChsT": "天和",
        "nameJp": "天和",
        "nameEn": "Blessing of Heaven",
        "nameKr": "천화",
        "xuanshang": 0,
        "yiman": 1,
        "fanMenqing": 13,
        "fanFulu": 13,
        "showIndex": 350,
        "sound": "fan_tianhu",
        "isGuyi": 0,
        "rarity": 11,
        "showRange_1": "",
        "showRange_2": "",
        "mergeId": 0,
        "mark": 0
    },
    {
        "id": 36,
        "nameChs": "地和",
        "nameChsT": "地和",
        "nameJp": "地和",
        "nameEn": "Blessing of Earth",
        "nameKr": "지화",
        "xuanshang": 0,
        "yiman": 1,
        "fanMenqing": 13,
        "fanFulu": 13,
        "showIndex": 360,
        "sound": "fan_dihu",
        "isGuyi": 0,
        "rarity": 12,
        "showRange_1": "",
        "showRange_2": "",
        "mergeId": 0,
        "mark": 0
    },
    {
        "id": 37,
        "nameChs": "大三元",
        "nameChsT": "大三元",
        "nameJp": "大三元",
        "nameEn": "Big Three Dragons",
        "nameKr": "대삼원",
        "xuanshang": 0,
        "yiman": 1,
        "fanMenqing": 13,
        "fanFulu": 13,
        "showIndex": 370,
        "sound": "fan_dasanyuan",
        "isGuyi": 0,
        "rarity": 34,
        "showRange_1": "",
        "showRange_2": "",
        "mergeId": 0,
        "mark": 0
    },
    {
        "id": 38,
        "nameChs": "四暗刻",
        "nameChsT": "四暗刻",
        "nameJp": "四暗刻",
        "nameEn": "Four Concealed Triplets",
        "nameKr": "스안커",
        "xuanshang": 0,
        "yiman": 1,
        "fanMenqing": 13,
        "fanFulu": 13,
        "showIndex": 380,
        "sound": "fan_sianke",
        "isGuyi": 0,
        "rarity": 33,
        "showRange_1": "",
        "showRange_2": "",
        "mergeId": 0,
        "mark": 0
    },
    {
        "id": 39,
        "nameChs": "字一色",
        "nameChsT": "字一色",
        "nameJp": "字一色",
        "nameEn": "All Honors",
        "nameKr": "자일색",
        "xuanshang": 0,
        "yiman": 1,
        "fanMenqing": 13,
        "fanFulu": 13,
        "showIndex": 390,
        "sound": "fan_ziyise",
        "isGuyi": 0,
        "rarity": 32,
        "showRange_1": "",
        "showRange_2": "",
        "mergeId": 0,
        "mark": 0
    },
    {
        "id": 40,
        "nameChs": "绿一色",
        "nameChsT": "綠一色",
        "nameJp": "緑一色",
        "nameEn": "All Green",
        "nameKr": "녹일색",
        "xuanshang": 0,
        "yiman": 1,
        "fanMenqing": 13,
        "fanFulu": 13,
        "showIndex": 400,
        "sound": "fan_lvyise",
        "isGuyi": 0,
        "rarity": 24,
        "showRange_1": "",
        "showRange_2": "",
        "mergeId": 0,
        "mark": 0
    },
    {
        "id": 41,
        "nameChs": "清老头",
        "nameChsT": "清老頭",
        "nameJp": "清老頭",
        "nameEn": "All Terminals",
        "nameKr": "청노두",
        "xuanshang": 0,
        "yiman": 1,
        "fanMenqing": 13,
        "fanFulu": 13,
        "showIndex": 410,
        "sound": "fan_qinglaotou",
        "isGuyi": 0,
        "rarity": 22,
        "showRange_1": "",
        "showRange_2": "",
        "mergeId": 0,
        "mark": 0
    },
    {
        "id": 42,
        "nameChs": "国士无双",
        "nameChsT": "國士無雙",
        "nameJp": "国士無双",
        "nameEn": "Thirteen Orphans",
        "nameKr": "국사무쌍",
        "xuanshang": 0,
        "yiman": 1,
        "fanMenqing": 13,
        "fanFulu": 13,
        "showIndex": 420,
        "sound": "fan_guoshiwushuang",
        "isGuyi": 0,
        "rarity": 31,
        "showRange_1": "",
        "showRange_2": "",
        "mergeId": 0,
        "mark": 0
    },
    {
        "id": 43,
        "nameChs": "小四喜",
        "nameChsT": "小四喜",
        "nameJp": "小四喜",
        "nameEn": "Four Little Winds",
        "nameKr": "소사희",
        "xuanshang": 0,
        "yiman": 1,
        "fanMenqing": 13,
        "fanFulu": 13,
        "showIndex": 430,
        "sound": "fan_xiaosixi",
        "isGuyi": 0,
        "rarity": 23,
        "showRange_1": "",
        "showRange_2": "",
        "mergeId": 0,
        "mark": 0
    },
    {
        "id": 44,
        "nameChs": "四杠子",
        "nameChsT": "四槓子",
        "nameJp": "四槓子",
        "nameEn": "Four Quads",
        "nameKr": "스깡쯔",
        "xuanshang": 0,
        "yiman": 1,
        "fanMenqing": 13,
        "fanFulu": 13,
        "showIndex": 440,
        "sound": "fan_sigangzi",
        "isGuyi": 0,
        "rarity": 13,
        "showRange_1": "",
        "showRange_2": "",
        "mergeId": 0,
        "mark": 0
    },
    {
        "id": 45,
        "nameChs": "九莲宝灯",
        "nameChsT": "九蓮寶燈",
        "nameJp": "九蓮宝燈",
        "nameEn": "Nine Gates",
        "nameKr": "구련보등",
        "xuanshang": 0,
        "yiman": 1,
        "fanMenqing": 13,
        "fanFulu": 13,
        "showIndex": 450,
        "sound": "fan_jiulianbaodeng",
        "isGuyi": 0,
        "rarity": 21,
        "showRange_1": "",
        "showRange_2": "",
        "mergeId": 0,
        "mark": 0
    },
    {
        "id": 46,
        "nameChs": "八连庄",
        "nameChsT": "八連莊",
        "nameJp": "八連荘",
        "nameEn": "Eight-time East Staying",
        "nameKr": "팔연장",
        "xuanshang": 0,
        "yiman": 1,
        "fanMenqing": 13,
        "fanFulu": 13,
        "showIndex": 460,
        "sound": "",
        "isGuyi": 0,
        "rarity": 0,
        "showRange_1": "-1",
        "showRange_2": "-1",
        "mergeId": 0,
        "mark": 0
    },
    {
        "id": 47,
        "nameChs": "纯正九莲宝灯",
        "nameChsT": "純正九蓮寶燈",
        "nameJp": "純正九蓮宝燈",
        "nameEn": "True Nine Gates",
        "nameKr": "순정구련보등",
        "xuanshang": 0,
        "yiman": 2,
        "fanMenqing": 26,
        "fanFulu": 26,
        "showIndex": 470,
        "sound": "fan_chunzhengjiulianbaodeng",
        "isGuyi": 0,
        "rarity": 14,
        "showRange_1": "",
        "showRange_2": "",
        "mergeId": 0,
        "mark": 0
    },
    {
        "id": 48,
        "nameChs": "四暗刻单骑",
        "nameChsT": "四暗刻單騎",
        "nameJp": "四暗刻単騎",
        "nameEn": "Single-wait Four Concealed Triplets",
        "nameKr": "스안커 단기",
        "xuanshang": 0,
        "yiman": 2,
        "fanMenqing": 26,
        "fanFulu": 26,
        "showIndex": 480,
        "sound": "fan_siankedanqi",
        "isGuyi": 0,
        "rarity": 17,
        "showRange_1": "",
        "showRange_2": "",
        "mergeId": 0,
        "mark": 0
    },
    {
        "id": 49,
        "nameChs": "国士无双十三面",
        "nameChsT": "國士無雙十三面",
        "nameJp": "国士無双十三面待ち",
        "nameEn": "Thirteen-wait Thirteen Orphans",
        "nameKr": "국사무쌍 13면 대기",
        "xuanshang": 0,
        "yiman": 2,
        "fanMenqing": 26,
        "fanFulu": 26,
        "showIndex": 490,
        "sound": "fan_guoshishisanmian",
        "isGuyi": 0,
        "rarity": 15,
        "showRange_1": "",
        "showRange_2": "",
        "mergeId": 0,
        "mark": 0
    },
    {
        "id": 50,
        "nameChs": "大四喜",
        "nameChsT": "大四喜",
        "nameJp": "大四喜",
        "nameEn": "Four Big Winds",
        "nameKr": "대사희",
        "xuanshang": 0,
        "yiman": 2,
        "fanMenqing": 26,
        "fanFulu": 26,
        "showIndex": 500,
        "sound": "fan_dasixi",
        "isGuyi": 0,
        "rarity": 16,
        "showRange_1": "",
        "showRange_2": "",
        "mergeId": 0,
        "mark": 0
    },
    {
        "id": 51,
        "nameChs": "燕返",
        "nameChsT": "燕返",
        "nameJp": "燕返し",
        "nameEn": "Tsubame-gaeshi",
        "nameKr": "츠바메가에시",
        "xuanshang": 0,
        "yiman": 0,
        "fanMenqing": 1,
        "fanFulu": 1,
        "showIndex": 11,
        "sound": "",
        "isGuyi": 1,
        "rarity": 0,
        "showRange_1": "",
        "showRange_2": "",
        "mergeId": 0,
        "mark": 0
    },
    {
        "id": 52,
        "nameChs": "杠振",
        "nameChsT": "槓振",
        "nameJp": "槓振り",
        "nameEn": "Kanburi",
        "nameKr": "깡후리",
        "xuanshang": 0,
        "yiman": 0,
        "fanMenqing": 1,
        "fanFulu": 1,
        "showIndex": 12,
        "sound": "",
        "isGuyi": 1,
        "rarity": 0,
        "showRange_1": "",
        "showRange_2": "",
        "mergeId": 0,
        "mark": 0
    },
    {
        "id": 53,
        "nameChs": "十二落抬",
        "nameChsT": "十二落抬",
        "nameJp": "十二落抬",
        "nameEn": "Shiiaruraotai",
        "nameKr": "십이낙태",
        "xuanshang": 0,
        "yiman": 0,
        "fanMenqing": 1,
        "fanFulu": 1,
        "showIndex": 13,
        "sound": "",
        "isGuyi": 1,
        "rarity": 0,
        "showRange_1": "",
        "showRange_2": "",
        "mergeId": 0,
        "mark": 0
    },
    {
        "id": 54,
        "nameChs": "五门齐",
        "nameChsT": "五門齊",
        "nameJp": "五門斉",
        "nameEn": "Uumensai",
        "nameKr": "오문제",
        "xuanshang": 0,
        "yiman": 0,
        "fanMenqing": 2,
        "fanFulu": 2,
        "showIndex": 293,
        "sound": "",
        "isGuyi": 1,
        "rarity": 0,
        "showRange_1": "",
        "showRange_2": "",
        "mergeId": 0,
        "mark": 0
    },
    {
        "id": 55,
        "nameChs": "三连刻",
        "nameChsT": "三連刻",
        "nameJp": "三連刻",
        "nameEn": "Three Chained Triplets",
        "nameKr": "삼연각",
        "xuanshang": 0,
        "yiman": 0,
        "fanMenqing": 2,
        "fanFulu": 2,
        "showIndex": 291,
        "sound": "",
        "isGuyi": 1,
        "rarity": 0,
        "showRange_1": "",
        "showRange_2": "",
        "mergeId": 0,
        "mark": 0
    },
    {
        "id": 56,
        "nameChs": "一色三同顺",
        "nameChsT": "一色三同順",
        "nameJp": "一色三順",
        "nameEn": "Pure Triple Chow",
        "nameKr": "일색삼순",
        "xuanshang": 0,
        "yiman": 0,
        "fanMenqing": 3,
        "fanFulu": 2,
        "showIndex": 292,
        "sound": "",
        "isGuyi": 1,
        "rarity": 0,
        "showRange_1": "",
        "showRange_2": "",
        "mergeId": 0,
        "mark": 0
    },
    {
        "id": 57,
        "nameChs": "一筒摸月",
        "nameChsT": "一筒摸月",
        "nameJp": "一筒摸月",
        "nameEn": "Iipinmoyue",
        "nameKr": "일통모월",
        "xuanshang": 0,
        "yiman": 0,
        "fanMenqing": 5,
        "fanFulu": 5,
        "showIndex": 301,
        "sound": "",
        "isGuyi": 1,
        "rarity": 0,
        "showRange_1": "",
        "showRange_2": "",
        "mergeId": 0,
        "mark": 0
    },
    {
        "id": 58,
        "nameChs": "九筒捞鱼",
        "nameChsT": "九筒撈魚",
        "nameJp": "九筒撈魚",
        "nameEn": "Chuupinraoyui",
        "nameKr": "구통노어",
        "xuanshang": 0,
        "yiman": 0,
        "fanMenqing": 5,
        "fanFulu": 5,
        "showIndex": 302,
        "sound": "",
        "isGuyi": 1,
        "rarity": 0,
        "showRange_1": "",
        "showRange_2": "",
        "mergeId": 0,
        "mark": 0
    },
    {
        "id": 59,
        "nameChs": "人和",
        "nameChsT": "人和",
        "nameJp": "人和",
        "nameEn": "Hand of Man",
        "nameKr": "인화",
        "xuanshang": 0,
        "yiman": 1,
        "fanMenqing": 13,
        "fanFulu": 13,
        "showIndex": 590,
        "sound": "",
        "isGuyi": 1,
        "rarity": 0,
        "showRange_1": "",
        "showRange_2": "",
        "mergeId": 0,
        "mark": 0
    },
    {
        "id": 60,
        "nameChs": "大车轮",
        "nameChsT": "大車輪",
        "nameJp": "大車輪",
        "nameEn": "Big Wheels",
        "nameKr": "대차륜",
        "xuanshang": 0,
        "yiman": 1,
        "fanMenqing": 13,
        "fanFulu": 13,
        "showIndex": 600,
        "sound": "",
        "isGuyi": 1,
        "rarity": 0,
        "showRange_1": "",
        "showRange_2": "",
        "mergeId": 0,
        "mark": 0
    },
    {
        "id": 61,
        "nameChs": "大竹林",
        "nameChsT": "大竹林",
        "nameJp": "大竹林",
        "nameEn": "Bamboo Forest",
        "nameKr": "대죽림",
        "xuanshang": 0,
        "yiman": 1,
        "fanMenqing": 13,
        "fanFulu": 13,
        "showIndex": 610,
        "sound": "",
        "isGuyi": 1,
        "rarity": 0,
        "showRange_1": "",
        "showRange_2": "",
        "mergeId": 0,
        "mark": 0
    },
    {
        "id": 62,
        "nameChs": "大数邻",
        "nameChsT": "大數鄰",
        "nameJp": "大数隣",
        "nameEn": "Numerous Neighbours",
        "nameKr": "대수린",
        "xuanshang": 0,
        "yiman": 1,
        "fanMenqing": 13,
        "fanFulu": 13,
        "showIndex": 620,
        "sound": "",
        "isGuyi": 1,
        "rarity": 0,
        "showRange_1": "1",
        "showRange_2": "",
        "mergeId": 0,
        "mark": 0
    },
    {
        "id": 63,
        "nameChs": "石上三年",
        "nameChsT": "石上三年",
        "nameJp": "石の上にも三年",
        "nameEn": "Ishinouenimosannen",
        "nameKr": "석상삼년",
        "xuanshang": 0,
        "yiman": 1,
        "fanMenqing": 13,
        "fanFulu": 13,
        "showIndex": 630,
        "sound": "",
        "isGuyi": 1,
        "rarity": 0,
        "showRange_1": "",
        "showRange_2": "",
        "mergeId": 0,
        "mark": 0
    },
    {
        "id": 64,
        "nameChs": "大七星",
        "nameChsT": "大七星",
        "nameJp": "大七星",
        "nameEn": "Big Seven Stars",
        "nameKr": "대칠성",
        "xuanshang": 0,
        "yiman": 2,
        "fanMenqing": 26,
        "fanFulu": 26,
        "showIndex": 640,
        "sound": "",
        "isGuyi": 1,
        "rarity": 0,
        "showRange_1": "",
        "showRange_2": "",
        "mergeId": 0,
        "mark": 0
    },
    {
        "id": 65,
        "nameChs": "人和",
        "nameChsT": "人和",
        "nameJp": "人和",
        "nameEn": "Hand of Man",
        "nameKr": "인화",
        "xuanshang": 0,
        "yiman": 0,
        "fanMenqing": 5,
        "fanFulu": 5,
        "showIndex": 591,
        "sound": "",
        "isGuyi": 1,
        "rarity": 0,
        "showRange_1": "",
        "showRange_2": "",
        "mergeId": 59,
        "mark": 0
    },
    {
        "id": 801,
        "nameChs": "绯",
        "nameChsT": "緋",
        "nameJp": "緋色ボーナス",
        "nameEn": "Crimson Bonus",
        "nameKr": "붉은색 보너스",
        "xuanshang": 1,
        "yiman": 0,
        "fanMenqing": 1,
        "fanFulu": 1,
        "showIndex": 801,
        "sound": "",
        "isGuyi": 0,
        "rarity": 0,
        "showRange_1": "-1",
        "showRange_2": "-1",
        "mergeId": 0,
        "mark": 0
    },
    {
        "id": 802,
        "nameChs": "苍",
        "nameChsT": "蒼",
        "nameJp": "蒼色ボーナス",
        "nameEn": "Azure Bonus",
        "nameKr": "푸른색 보너스",
        "xuanshang": 1,
        "yiman": 0,
        "fanMenqing": 1,
        "fanFulu": 1,
        "showIndex": 802,
        "sound": "",
        "isGuyi": 0,
        "rarity": 0,
        "showRange_1": "-1",
        "showRange_2": "-1",
        "mergeId": 0,
        "mark": 0
    },
    {
        "id": 803,
        "nameChs": "过载",
        "nameChsT": "過載",
        "nameJp": "過熱",
        "nameEn": "Weak",
        "nameKr": "과적",
        "xuanshang": 2,
        "yiman": 0,
        "fanMenqing": 2,
        "fanFulu": 2,
        "showIndex": 803,
        "sound": "",
        "isGuyi": 0,
        "rarity": 0,
        "showRange_1": "-1",
        "showRange_2": "-1",
        "mergeId": 0,
        "mark": 0
    },
    {
        "id": 804,
        "nameChs": "立直",
        "nameChsT": "立直",
        "nameJp": "立直",
        "nameEn": "Riichi",
        "nameKr": "리치",
        "xuanshang": 0,
        "yiman": 0,
        "fanMenqing": 2,
        "fanFulu": 2,
        "showIndex": 10,
        "sound": "fan_liqi",
        "isGuyi": 0,
        "rarity": 0,
        "showRange_1": "",
        "showRange_2": "",
        "mergeId": 2,
        "mark": 0
    },
    {
        "id": 805,
        "nameChs": "两立直",
        "nameChsT": "兩立直",
        "nameJp": "ダブル立直",
        "nameEn": "Double Riichi",
        "nameKr": "더블 리치",
        "xuanshang": 0,
        "yiman": 0,
        "fanMenqing": 3,
        "fanFulu": 3,
        "showIndex": 10,
        "sound": "fan_dliqi",
        "isGuyi": 0,
        "rarity": 0,
        "showRange_1": "",
        "showRange_2": "",
        "mergeId": 18,
        "mark": 0
    },
    {
        "id": 806,
        "nameChs": "真-立直",
        "nameChsT": "真-立直",
        "nameJp": "真・立直",
        "nameEn": "True Riichi",
        "nameKr": "진-리치",
        "xuanshang": 0,
        "yiman": 0,
        "fanMenqing": 3,
        "fanFulu": 3,
        "showIndex": 10,
        "sound": "fan_liqi",
        "isGuyi": 0,
        "rarity": 0,
        "showRange_1": "",
        "showRange_2": "",
        "mergeId": 2,
        "mark": 1
    },
    {
        "id": 807,
        "nameChs": "真-两立直",
        "nameChsT": "真-兩立直",
        "nameJp": "真・ダブル立直",
        "nameEn": "True Double Riichi",
        "nameKr": "진-더블 리치",
        "xuanshang": 0,
        "yiman": 0,
        "fanMenqing": 4,
        "fanFulu": 4,
        "showIndex": 10,
        "sound": "fan_dliqi",
        "isGuyi": 0,
        "rarity": 0,
        "showRange_1": "",
        "showRange_2": "",
        "mergeId": 18,
        "mark": 1
    },
    {
        "id": 808,
        "nameChs": "极-立直",
        "nameChsT": "極-立直",
        "nameJp": "極・立直",
        "nameEn": "Extreme Riichi",
        "nameKr": "극-리치",
        "xuanshang": 0,
        "yiman": 0,
        "fanMenqing": 5,
        "fanFulu": 5,
        "showIndex": 10,
        "sound": "fan_liqi",
        "isGuyi": 0,
        "rarity": 0,
        "showRange_1": "",
        "showRange_2": "",
        "mergeId": 2,
        "mark": 1
    },
    {
        "id": 809,
        "nameChs": "极-两立直",
        "nameChsT": "極-兩立直",
        "nameJp": "極・ダブル立直",
        "nameEn": "Extreme Double Riichi",
        "nameKr": "극-더블 리치",
        "xuanshang": 0,
        "yiman": 0,
        "fanMenqing": 6,
        "fanFulu": 6,
        "showIndex": 10,
        "sound": "fan_dliqi",
        "isGuyi": 0,
        "rarity": 0,
        "showRange_1": "",
        "showRange_2": "",
        "mergeId": 18,
        "mark": 1
    },
    {
        "id": 1000,
        "nameChs": "根",
        "nameChsT": "根",
        "nameJp": "根",
        "nameEn": "Root",
        "nameKr": "루트",
        "xuanshang": 0,
        "yiman": 0,
        "fanMenqing": 1,
        "fanFulu": 1,
        "showIndex": 1084,
        "sound": "scfan_gen",
        "isGuyi": 2,
        "rarity": 0,
        "showRange_1": "-1",
        "showRange_2": "-1",
        "mergeId": 0,
        "mark": 0
    },
    {
        "id": 1001,
        "nameChs": "杠上花",
        "nameChsT": "槓上花",
        "nameJp": "嶺上開花",
        "nameEn": "After a Kan",
        "nameKr": "영상개화",
        "xuanshang": 0,
        "yiman": 0,
        "fanMenqing": 1,
        "fanFulu": 1,
        "showIndex": 1081,
        "sound": "fan_lingshang",
        "isGuyi": 2,
        "rarity": 0,
        "showRange_1": "-1",
        "showRange_2": "-1",
        "mergeId": 0,
        "mark": 0
    },
    {
        "id": 1002,
        "nameChs": "杠上炮",
        "nameChsT": "槓上炮",
        "nameJp": "嶺上放銃",
        "nameEn": "Dealing into Win after Kan",
        "nameKr": "영상방총",
        "xuanshang": 0,
        "yiman": 0,
        "fanMenqing": 1,
        "fanFulu": 1,
        "showIndex": 1802,
        "sound": "scfan_lingshangfangchong",
        "isGuyi": 2,
        "rarity": 0,
        "showRange_1": "-1",
        "showRange_2": "-1",
        "mergeId": 0,
        "mark": 0
    },
    {
        "id": 1003,
        "nameChs": "底和",
        "nameChsT": "底和",
        "nameJp": "無番和",
        "nameEn": "Yakuless Win",
        "nameKr": "무번화",
        "xuanshang": 0,
        "yiman": 0,
        "fanMenqing": 1,
        "fanFulu": 1,
        "showIndex": 1000,
        "sound": "",
        "isGuyi": 2,
        "rarity": 0,
        "showRange_1": "-1",
        "showRange_2": "-1",
        "mergeId": 0,
        "mark": 0
    },
    {
        "id": 1004,
        "nameChs": "枪杠",
        "nameChsT": "搶槓",
        "nameJp": "槍槓",
        "nameEn": "Robbing a Kan",
        "nameKr": "창깡",
        "xuanshang": 0,
        "yiman": 0,
        "fanMenqing": 1,
        "fanFulu": 1,
        "showIndex": 1083,
        "sound": "fan_qianggang",
        "isGuyi": 2,
        "rarity": 0,
        "showRange_1": "-1",
        "showRange_2": "-1",
        "mergeId": 0,
        "mark": 0
    },
    {
        "id": 1021,
        "nameChs": "海底捞月",
        "nameChsT": "海底捞月",
        "nameJp": "海底摸月",
        "nameEn": "Under the Sea",
        "nameKr": "해저로월",
        "xuanshang": 0,
        "yiman": 0,
        "fanMenqing": 1,
        "fanFulu": 1,
        "showIndex": 1014,
        "sound": "fan_haidi",
        "isGuyi": 2,
        "rarity": 0,
        "showRange_1": "-1",
        "showRange_2": "-1",
        "mergeId": 0,
        "mark": 0
    },
    {
        "id": 1005,
        "nameChs": "对对和",
        "nameChsT": "對對和",
        "nameJp": "対々和",
        "nameEn": "All Triplets",
        "nameKr": "또이또이",
        "xuanshang": 0,
        "yiman": 0,
        "fanMenqing": 2,
        "fanFulu": 2,
        "showIndex": 1020,
        "sound": "fan_duiduihu",
        "isGuyi": 2,
        "rarity": 0,
        "showRange_1": "-1",
        "showRange_2": "-1",
        "mergeId": 0,
        "mark": 0
    },
    {
        "id": 1006,
        "nameChs": "清一色",
        "nameChsT": "清一色",
        "nameJp": "清一色",
        "nameEn": "Full Flush",
        "nameKr": "청일색",
        "xuanshang": 0,
        "yiman": 0,
        "fanMenqing": 3,
        "fanFulu": 3,
        "showIndex": 1021,
        "sound": "fan_qingyise",
        "isGuyi": 2,
        "rarity": 0,
        "showRange_1": "-1",
        "showRange_2": "-1",
        "mergeId": 0,
        "mark": 0
    },
    {
        "id": 1007,
        "nameChs": "七对子",
        "nameChsT": "七對子",
        "nameJp": "七対子",
        "nameEn": "Seven Pairs",
        "nameKr": "치또이쯔",
        "xuanshang": 0,
        "yiman": 0,
        "fanMenqing": 3,
        "fanFulu": 3,
        "showIndex": 1022,
        "sound": "fan_qiduizi",
        "isGuyi": 2,
        "rarity": 0,
        "showRange_1": "-1",
        "showRange_2": "-1",
        "mergeId": 0,
        "mark": 0
    },
    {
        "id": 1008,
        "nameChs": "带幺九",
        "nameChsT": "帶么九",
        "nameJp": "帯幺九",
        "nameEn": "Terminals in All Sets",
        "nameKr": "대요구",
        "xuanshang": 0,
        "yiman": 0,
        "fanMenqing": 3,
        "fanFulu": 3,
        "showIndex": 1023,
        "sound": "scfan_daiyaojiu",
        "isGuyi": 2,
        "rarity": 0,
        "showRange_1": "-1",
        "showRange_2": "-1",
        "mergeId": 0,
        "mark": 0
    },
    {
        "id": 1009,
        "nameChs": "金钩钓",
        "nameChsT": "金鈎釣",
        "nameJp": "金勾釣",
        "nameEn": "Single Wait after 4 Triplets",
        "nameKr": "금구조",
        "xuanshang": 0,
        "yiman": 0,
        "fanMenqing": 3,
        "fanFulu": 3,
        "showIndex": 1024,
        "sound": "scfan_jingoudiao",
        "isGuyi": 2,
        "rarity": 0,
        "showRange_1": "-1",
        "showRange_2": "-1",
        "mergeId": 0,
        "mark": 0
    },
    {
        "id": 1010,
        "nameChs": "清对",
        "nameChsT": "清對",
        "nameJp": "清対",
        "nameEn": "Pure Triplets",
        "nameKr": "청또이",
        "xuanshang": 0,
        "yiman": 0,
        "fanMenqing": 4,
        "fanFulu": 4,
        "showIndex": 1010,
        "sound": "scfan_qingdui",
        "isGuyi": 2,
        "rarity": 0,
        "showRange_1": "-1",
        "showRange_2": "-1",
        "mergeId": 0,
        "mark": 0
    },
    {
        "id": 1011,
        "nameChs": "将对",
        "nameChsT": "將對",
        "nameJp": "将対",
        "nameEn": "2/5/8 Triplets",
        "nameKr": "장또이",
        "xuanshang": 0,
        "yiman": 0,
        "fanMenqing": 4,
        "fanFulu": 4,
        "showIndex": 1011,
        "sound": "scfan_jiangdui",
        "isGuyi": 2,
        "rarity": 0,
        "showRange_1": "-1",
        "showRange_2": "-1",
        "mergeId": 0,
        "mark": 0
    },
    {
        "id": 1012,
        "nameChs": "龙七对",
        "nameChsT": "龍七對",
        "nameJp": "龍七対",
        "nameEn": "Seven Pairs with One Duplicate",
        "nameKr": "용치또이",
        "xuanshang": 0,
        "yiman": 0,
        "fanMenqing": 4,
        "fanFulu": 4,
        "showIndex": 1012,
        "sound": "scfan_longqidui",
        "isGuyi": 2,
        "rarity": 0,
        "showRange_1": "-1",
        "showRange_2": "-1",
        "mergeId": 0,
        "mark": 0
    },
    {
        "id": 1013,
        "nameChs": "清七对",
        "nameChsT": "清七對",
        "nameJp": "清七対",
        "nameEn": "Pure Seven Pairs",
        "nameKr": "청치또이",
        "xuanshang": 0,
        "yiman": 0,
        "fanMenqing": 5,
        "fanFulu": 5,
        "showIndex": 1013,
        "sound": "scfan_qingqidui",
        "isGuyi": 2,
        "rarity": 0,
        "showRange_1": "-1",
        "showRange_2": "-1",
        "mergeId": 0,
        "mark": 0
    },
    {
        "id": 1020,
        "nameChs": "清幺九",
        "nameChsT": "清么九",
        "nameJp": "清幺九",
        "nameEn": "All Terminals",
        "nameKr": "청요구",
        "xuanshang": 0,
        "yiman": 0,
        "fanMenqing": 5,
        "fanFulu": 5,
        "showIndex": 1014,
        "sound": "scfan_qingyaojiu",
        "isGuyi": 2,
        "rarity": 0,
        "showRange_1": "-1",
        "showRange_2": "-1",
        "mergeId": 0,
        "mark": 0
    },
    {
        "id": 1014,
        "nameChs": "清金钩钓",
        "nameChsT": "清金鈎釣",
        "nameJp": "清金勾釣",
        "nameEn": "Pure Single Wait after 4 Triplets",
        "nameKr": "청금구조",
        "xuanshang": 0,
        "yiman": 0,
        "fanMenqing": 5,
        "fanFulu": 5,
        "showIndex": 1015,
        "sound": "scfan_qingjindoudiao",
        "isGuyi": 2,
        "rarity": 0,
        "showRange_1": "-1",
        "showRange_2": "-1",
        "mergeId": 0,
        "mark": 0
    },
    {
        "id": 1015,
        "nameChs": "清龙七对",
        "nameChsT": "清龍七對",
        "nameJp": "清龍七対",
        "nameEn": "Pure Seven Pairs with One Duplicate",
        "nameKr": "청룡치또이",
        "xuanshang": 0,
        "yiman": 0,
        "fanMenqing": 6,
        "fanFulu": 6,
        "showIndex": 1003,
        "sound": "scfan_qinglongqidui",
        "isGuyi": 2,
        "rarity": 0,
        "showRange_1": "-1",
        "showRange_2": "-1",
        "mergeId": 0,
        "mark": 0
    },
    {
        "id": 1016,
        "nameChs": "十八罗汉",
        "nameChsT": "十八羅漢",
        "nameJp": "十八羅漢",
        "nameEn": "Four Quads",
        "nameKr": "십팔라한",
        "xuanshang": 0,
        "yiman": 0,
        "fanMenqing": 6,
        "fanFulu": 6,
        "showIndex": 1004,
        "sound": "scfan_shibaluohan",
        "isGuyi": 2,
        "rarity": 0,
        "showRange_1": "-1",
        "showRange_2": "-1",
        "mergeId": 0,
        "mark": 0
    },
    {
        "id": 1017,
        "nameChs": "清十八罗汉",
        "nameChsT": "清十八羅漢",
        "nameJp": "清十八羅漢",
        "nameEn": "Pure Four Quads",
        "nameKr": "청십팔라한",
        "xuanshang": 0,
        "yiman": 0,
        "fanMenqing": 6,
        "fanFulu": 6,
        "showIndex": 1005,
        "sound": "scfan_qingshibaluohan",
        "isGuyi": 2,
        "rarity": 0,
        "showRange_1": "-1",
        "showRange_2": "-1",
        "mergeId": 0,
        "mark": 0
    },
    {
        "id": 1018,
        "nameChs": "天和",
        "nameChsT": "天和",
        "nameJp": "天和",
        "nameEn": "Blessing of Heaven",
        "nameKr": "천화",
        "xuanshang": 0,
        "yiman": 0,
        "fanMenqing": 6,
        "fanFulu": 6,
        "showIndex": 1001,
        "sound": "fan_tianhu",
        "isGuyi": 2,
        "rarity": 0,
        "showRange_1": "-1",
        "showRange_2": "-1",
        "mergeId": 0,
        "mark": 0
    },
    {
        "id": 1019,
        "nameChs": "地和",
        "nameChsT": "地和",
        "nameJp": "地和",
        "nameEn": "Blessing of Earth",
        "nameKr": "지화",
        "xuanshang": 0,
        "yiman": 0,
        "fanMenqing": 6,
        "fanFulu": 6,
        "showIndex": 1002,
        "sound": "fan_dihu",
        "isGuyi": 2,
        "rarity": 0,
        "showRange_1": "-1",
        "showRange_2": "-1",
        "mergeId": 0,
        "mark": 0
    }
]