[
    {
        "id": 26040301,
        "activityId": 260403,
        "tabId": 1
    },
    {
        "id": 26040302,
        "activityId": 260403,
        "tabId": 1
    },
    {
        "id": 26040303,
        "activityId": 260403,
        "tabId": 1
    },
    {
        "id": 26040304,
        "activityId": 260403,
        "tabId": 1
    },
    {
        "id": 26040305,
        "activityId": 260403,
        "tabId": 1
    },
    {
        "id": 26040306,
        "activityId": 260403,
        "tabId": 1
    },
    {
        "id": 26040307,
        "activityId": 260403,
        "tabId": 1
    },
    {
        "id": 26040308,
        "activityId": 260403,
        "tabId": 1
    },
    {
        "id": 26040309,
        "activityId": 260403,
        "tabId": 1
    },
    {
        "id": 26040310,
        "activityId": 260403,
        "tabId": 1
    },
    {
        "id": 26040311,
        "activityId": 260403,
        "tabId": 1
    },
    {
        "id": 26040312,
        "activityId": 260403,
        "tabId": 1
    },
    {
        "id": 26040313,
        "activityId": 260403,
        "tabId": 1
    },
    {
        "id": 26040314,
        "activityId": 260403,
        "tabId": 1
    },
    {
        "id": 26040315,
        "activityId": 260403,
        "tabId": 1
    },
    {
        "id": 26040316,
        "activityId": 260403,
        "tabId": 1
    },
    {
        "id": 26040317,
        "activityId": 260403,
        "tabId": 1
    },
    {
        "id": 26040318,
        "activityId": 260403,
        "tabId": 1
    },
    {
        "id": 26040319,
        "activityId": 260403,
        "tabId": 1
    },
    {
        "id": 26040320,
        "activityId": 260403,
        "tabId": 1
    },
    {
        "id": 26040321,
        "activityId": 260403,
        "tabId": 2
    },
    {
        "id": 26040322,
        "activityId": 260403,
        "tabId": 2
    },
    {
        "id": 26040323,
        "activityId": 260403,
        "tabId": 2
    },
    {
        "id": 26040324,
        "activityId": 260403,
        "tabId": 2
    },
    {
        "id": 26040325,
        "activityId": 260403,
        "tabId": 2
    },
    {
        "id": 26040326,
        "activityId": 260403,
        "tabId": 2
    },
    {
        "id": 26040327,
        "activityId": 260403,
        "tabId": 2
    },
    {
        "id": 26040328,
        "activityId": 260403,
        "tabId": 2
    },
    {
        "id": 26040329,
        "activityId": 260403,
        "tabId": 2
    },
    {
        "id": 26040330,
        "activityId": 260403,
        "tabId": 2
    },
    {
        "id": 26040331,
        "activityId": 260403,
        "tabId": 2
    },
    {
        "id": 26040332,
        "activityId": 260403,
        "tabId": 2
    },
    {
        "id": 26040333,
        "activityId": 260403,
        "tabId": 2
    },
    {
        "id": 26040334,
        "activityId": 260403,
        "tabId": 2
    },
    {
        "id": 26040335,
        "activityId": 260403,
        "tabId": 3
    },
    {
        "id": 26040336,
        "activityId": 260403,
        "tabId": 3
    },
    {
        "id": 26040337,
        "activityId": 260403,
        "tabId": 3
    },
    {
        "id": 26040338,
        "activityId": 260403,
        "tabId": 3
    },
    {
        "id": 26040339,
        "activityId": 260403,
        "tabId": 3
    },
    {
        "id": 26040340,
        "activityId": 260403,
        "tabId": 3
    },
    {
        "id": 26040341,
        "activityId": 260403,
        "tabId": 3
    },
    {
        "id": 26040342,
        "activityId": 260403,
        "tabId": 3
    },
    {
        "id": 26040343,
        "activityId": 260403,
        "tabId": 3
    },
    {
        "id": 26040344,
        "activityId": 260403,
        "tabId": 3
    },
    {
        "id": 26040345,
        "activityId": 260403,
        "tabId": 3
    },
    {
        "id": 26040346,
        "activityId": 260403,
        "tabId": 3
    },
    {
        "id": 26040347,
        "activityId": 260403,
        "tabId": 3
    },
    {
        "id": 26040348,
        "activityId": 260403,
        "tabId": 3
    }
]