[
    {
        "mapId": 106401,
        "location": 0,
        "posX": 4,
        "posY": 0,
        "pieceFace": 0,
        "type": 0,
        "param": 0,
        "bonusType": 0,
        "worth": 1250
    },
    {
        "mapId": 106401,
        "location": 1,
        "posX": 5,
        "posY": 0,
        "pieceFace": 0,
        "type": 1,
        "param": 60101,
        "bonusType": 1,
        "worth": 1250
    },
    {
        "mapId": 106401,
        "location": 2,
        "posX": 6,
        "posY": 0,
        "pieceFace": 0,
        "type": 1,
        "param": 60103,
        "bonusType": 2,
        "worth": 15000
    },
    {
        "mapId": 106401,
        "location": 3,
        "posX": 6,
        "posY": 1,
        "pieceFace": 0,
        "type": 1,
        "param": 60101,
        "bonusType": 1,
        "worth": 1250
    },
    {
        "mapId": 106401,
        "location": 4,
        "posX": 6,
        "posY": 2,
        "pieceFace": 0,
        "type": 4,
        "param": 0,
        "bonusType": 5,
        "worth": 1250
    },
    {
        "mapId": 106401,
        "location": 5,
        "posX": 6,
        "posY": 3,
        "pieceFace": 0,
        "type": 1,
        "param": 60101,
        "bonusType": 1,
        "worth": 1250
    },
    {
        "mapId": 106401,
        "location": 6,
        "posX": 6,
        "posY": 4,
        "pieceFace": 0,
        "type": 1,
        "param": 60102,
        "bonusType": 3,
        "worth": 1250
    },
    {
        "mapId": 106401,
        "location": 7,
        "posX": 6,
        "posY": 5,
        "pieceFace": 0,
        "type": 1,
        "param": 60101,
        "bonusType": 1,
        "worth": 1250
    },
    {
        "mapId": 106401,
        "location": 8,
        "posX": 6,
        "posY": 6,
        "pieceFace": 0,
        "type": 1,
        "param": 60103,
        "bonusType": 2,
        "worth": 15000
    },
    {
        "mapId": 106401,
        "location": 9,
        "posX": 5,
        "posY": 6,
        "pieceFace": 0,
        "type": 1,
        "param": 60101,
        "bonusType": 1,
        "worth": 1250
    },
    {
        "mapId": 106401,
        "location": 10,
        "posX": 4,
        "posY": 6,
        "pieceFace": 0,
        "type": 1,
        "param": 60104,
        "bonusType": 4,
        "worth": 50000
    },
    {
        "mapId": 106401,
        "location": 11,
        "posX": 3,
        "posY": 6,
        "pieceFace": 0,
        "type": 1,
        "param": 60101,
        "bonusType": 1,
        "worth": 1250
    },
    {
        "mapId": 106401,
        "location": 12,
        "posX": 2,
        "posY": 6,
        "pieceFace": 0,
        "type": 4,
        "param": 0,
        "bonusType": 5,
        "worth": 1250
    },
    {
        "mapId": 106401,
        "location": 13,
        "posX": 1,
        "posY": 6,
        "pieceFace": 0,
        "type": 1,
        "param": 60101,
        "bonusType": 1,
        "worth": 1250
    },
    {
        "mapId": 106401,
        "location": 14,
        "posX": 0,
        "posY": 6,
        "pieceFace": 0,
        "type": 1,
        "param": 60103,
        "bonusType": 2,
        "worth": 15000
    },
    {
        "mapId": 106401,
        "location": 15,
        "posX": 0,
        "posY": 5,
        "pieceFace": 0,
        "type": 1,
        "param": 60101,
        "bonusType": 1,
        "worth": 1250
    },
    {
        "mapId": 106401,
        "location": 16,
        "posX": 0,
        "posY": 4,
        "pieceFace": 0,
        "type": 1,
        "param": 60101,
        "bonusType": 1,
        "worth": 1250
    },
    {
        "mapId": 106401,
        "location": 17,
        "posX": 1,
        "posY": 4,
        "pieceFace": 0,
        "type": 3,
        "param": 0,
        "bonusType": 6,
        "worth": 1250
    },
    {
        "mapId": 106401,
        "location": 18,
        "posX": 1,
        "posY": 3,
        "pieceFace": 0,
        "type": 1,
        "param": 60101,
        "bonusType": 1,
        "worth": 1250
    },
    {
        "mapId": 106401,
        "location": 19,
        "posX": 1,
        "posY": 2,
        "pieceFace": 0,
        "type": 1,
        "param": 60101,
        "bonusType": 1,
        "worth": 1250
    },
    {
        "mapId": 106401,
        "location": 20,
        "posX": 0,
        "posY": 2,
        "pieceFace": 0,
        "type": 4,
        "param": 0,
        "bonusType": 5,
        "worth": 1250
    },
    {
        "mapId": 106401,
        "location": 21,
        "posX": 0,
        "posY": 1,
        "pieceFace": 0,
        "type": 1,
        "param": 60101,
        "bonusType": 1,
        "worth": 1250
    },
    {
        "mapId": 106401,
        "location": 22,
        "posX": 0,
        "posY": 0,
        "pieceFace": 0,
        "type": 1,
        "param": 60103,
        "bonusType": 2,
        "worth": 15000
    },
    {
        "mapId": 106401,
        "location": 23,
        "posX": 1,
        "posY": 0,
        "pieceFace": 0,
        "type": 1,
        "param": 60101,
        "bonusType": 1,
        "worth": 1250
    },
    {
        "mapId": 106401,
        "location": 24,
        "posX": 2,
        "posY": 0,
        "pieceFace": 0,
        "type": 1,
        "param": 60102,
        "bonusType": 3,
        "worth": 1250
    },
    {
        "mapId": 106401,
        "location": 25,
        "posX": 2,
        "posY": 1,
        "pieceFace": 0,
        "type": 1,
        "param": 60101,
        "bonusType": 1,
        "worth": 1250
    },
    {
        "mapId": 106401,
        "location": 26,
        "posX": 3,
        "posY": 1,
        "pieceFace": 0,
        "type": 4,
        "param": 0,
        "bonusType": 5,
        "worth": 1250
    },
    {
        "mapId": 106401,
        "location": 27,
        "posX": 4,
        "posY": 1,
        "pieceFace": 0,
        "type": 1,
        "param": 60101,
        "bonusType": 1,
        "worth": 1250
    },
    {
        "mapId": 107301,
        "location": 0,
        "posX": 4,
        "posY": 0,
        "pieceFace": 0,
        "type": 0,
        "param": 0,
        "bonusType": 0,
        "worth": 1250
    },
    {
        "mapId": 107301,
        "location": 1,
        "posX": 5,
        "posY": 0,
        "pieceFace": 0,
        "type": 1,
        "param": 60101,
        "bonusType": 1,
        "worth": 1250
    },
    {
        "mapId": 107301,
        "location": 2,
        "posX": 6,
        "posY": 0,
        "pieceFace": 0,
        "type": 1,
        "param": 60103,
        "bonusType": 2,
        "worth": 15000
    },
    {
        "mapId": 107301,
        "location": 3,
        "posX": 6,
        "posY": 1,
        "pieceFace": 0,
        "type": 1,
        "param": 60101,
        "bonusType": 1,
        "worth": 1250
    },
    {
        "mapId": 107301,
        "location": 4,
        "posX": 6,
        "posY": 2,
        "pieceFace": 0,
        "type": 4,
        "param": 0,
        "bonusType": 5,
        "worth": 1250
    },
    {
        "mapId": 107301,
        "location": 5,
        "posX": 6,
        "posY": 3,
        "pieceFace": 0,
        "type": 1,
        "param": 60101,
        "bonusType": 1,
        "worth": 1250
    },
    {
        "mapId": 107301,
        "location": 6,
        "posX": 6,
        "posY": 4,
        "pieceFace": 0,
        "type": 1,
        "param": 60102,
        "bonusType": 3,
        "worth": 1250
    },
    {
        "mapId": 107301,
        "location": 7,
        "posX": 6,
        "posY": 5,
        "pieceFace": 0,
        "type": 1,
        "param": 60101,
        "bonusType": 1,
        "worth": 1250
    },
    {
        "mapId": 107301,
        "location": 8,
        "posX": 6,
        "posY": 6,
        "pieceFace": 0,
        "type": 1,
        "param": 60103,
        "bonusType": 2,
        "worth": 15000
    },
    {
        "mapId": 107301,
        "location": 9,
        "posX": 5,
        "posY": 6,
        "pieceFace": 0,
        "type": 1,
        "param": 60101,
        "bonusType": 1,
        "worth": 1250
    },
    {
        "mapId": 107301,
        "location": 10,
        "posX": 4,
        "posY": 6,
        "pieceFace": 0,
        "type": 1,
        "param": 60104,
        "bonusType": 4,
        "worth": 50000
    },
    {
        "mapId": 107301,
        "location": 11,
        "posX": 3,
        "posY": 6,
        "pieceFace": 0,
        "type": 1,
        "param": 60101,
        "bonusType": 1,
        "worth": 1250
    },
    {
        "mapId": 107301,
        "location": 12,
        "posX": 2,
        "posY": 6,
        "pieceFace": 0,
        "type": 4,
        "param": 0,
        "bonusType": 5,
        "worth": 1250
    },
    {
        "mapId": 107301,
        "location": 13,
        "posX": 1,
        "posY": 6,
        "pieceFace": 0,
        "type": 1,
        "param": 60101,
        "bonusType": 1,
        "worth": 1250
    },
    {
        "mapId": 107301,
        "location": 14,
        "posX": 0,
        "posY": 6,
        "pieceFace": 0,
        "type": 1,
        "param": 60103,
        "bonusType": 2,
        "worth": 15000
    },
    {
        "mapId": 107301,
        "location": 15,
        "posX": 0,
        "posY": 5,
        "pieceFace": 0,
        "type": 1,
        "param": 60101,
        "bonusType": 1,
        "worth": 1250
    },
    {
        "mapId": 107301,
        "location": 16,
        "posX": 0,
        "posY": 4,
        "pieceFace": 0,
        "type": 1,
        "param": 60101,
        "bonusType": 1,
        "worth": 1250
    },
    {
        "mapId": 107301,
        "location": 17,
        "posX": 1,
        "posY": 4,
        "pieceFace": 0,
        "type": 3,
        "param": 0,
        "bonusType": 6,
        "worth": 1250
    },
    {
        "mapId": 107301,
        "location": 18,
        "posX": 1,
        "posY": 3,
        "pieceFace": 0,
        "type": 1,
        "param": 60101,
        "bonusType": 1,
        "worth": 1250
    },
    {
        "mapId": 107301,
        "location": 19,
        "posX": 1,
        "posY": 2,
        "pieceFace": 0,
        "type": 1,
        "param": 60101,
        "bonusType": 1,
        "worth": 1250
    },
    {
        "mapId": 107301,
        "location": 20,
        "posX": 0,
        "posY": 2,
        "pieceFace": 0,
        "type": 4,
        "param": 0,
        "bonusType": 5,
        "worth": 1250
    },
    {
        "mapId": 107301,
        "location": 21,
        "posX": 0,
        "posY": 1,
        "pieceFace": 0,
        "type": 1,
        "param": 60101,
        "bonusType": 1,
        "worth": 1250
    },
    {
        "mapId": 107301,
        "location": 22,
        "posX": 0,
        "posY": 0,
        "pieceFace": 0,
        "type": 1,
        "param": 60103,
        "bonusType": 2,
        "worth": 15000
    },
    {
        "mapId": 107301,
        "location": 23,
        "posX": 1,
        "posY": 0,
        "pieceFace": 0,
        "type": 1,
        "param": 60101,
        "bonusType": 1,
        "worth": 1250
    },
    {
        "mapId": 107301,
        "location": 24,
        "posX": 2,
        "posY": 0,
        "pieceFace": 0,
        "type": 1,
        "param": 60102,
        "bonusType": 3,
        "worth": 1250
    },
    {
        "mapId": 107301,
        "location": 25,
        "posX": 2,
        "posY": 1,
        "pieceFace": 0,
        "type": 1,
        "param": 60101,
        "bonusType": 1,
        "worth": 1250
    },
    {
        "mapId": 107301,
        "location": 26,
        "posX": 3,
        "posY": 1,
        "pieceFace": 0,
        "type": 4,
        "param": 0,
        "bonusType": 5,
        "worth": 1250
    },
    {
        "mapId": 107301,
        "location": 27,
        "posX": 4,
        "posY": 1,
        "pieceFace": 0,
        "type": 1,
        "param": 60101,
        "bonusType": 1,
        "worth": 1250
    },
    {
        "mapId": 109401,
        "location": 0,
        "posX": 0,
        "posY": 0,
        "pieceFace": 0,
        "type": 0,
        "param": 0,
        "bonusType": 0,
        "worth": 1200
    },
    {
        "mapId": 109401,
        "location": 1,
        "posX": 1,
        "posY": 0,
        "pieceFace": 0,
        "type": 1,
        "param": 60101,
        "bonusType": 1,
        "worth": 1200
    },
    {
        "mapId": 109401,
        "location": 2,
        "posX": 2,
        "posY": 0,
        "pieceFace": 0,
        "type": 1,
        "param": 60101,
        "bonusType": 1,
        "worth": 1200
    },
    {
        "mapId": 109401,
        "location": 3,
        "posX": 2,
        "posY": 1,
        "pieceFace": 0,
        "type": 4,
        "param": 0,
        "bonusType": 5,
        "worth": 1200
    },
    {
        "mapId": 109401,
        "location": 4,
        "posX": 3,
        "posY": 1,
        "pieceFace": 0,
        "type": 1,
        "param": 60101,
        "bonusType": 1,
        "worth": 1200
    },
    {
        "mapId": 109401,
        "location": 5,
        "posX": 4,
        "posY": 1,
        "pieceFace": 0,
        "type": 1,
        "param": 60101,
        "bonusType": 1,
        "worth": 1200
    },
    {
        "mapId": 109401,
        "location": 6,
        "posX": 4,
        "posY": 0,
        "pieceFace": 0,
        "type": 1,
        "param": 60103,
        "bonusType": 2,
        "worth": 15000
    },
    {
        "mapId": 109401,
        "location": 7,
        "posX": 5,
        "posY": 0,
        "pieceFace": 0,
        "type": 1,
        "param": 60101,
        "bonusType": 1,
        "worth": 1200
    },
    {
        "mapId": 109401,
        "location": 8,
        "posX": 6,
        "posY": 0,
        "pieceFace": 0,
        "type": 1,
        "param": 60102,
        "bonusType": 3,
        "worth": 1200
    },
    {
        "mapId": 109401,
        "location": 9,
        "posX": 6,
        "posY": 1,
        "pieceFace": 0,
        "type": 1,
        "param": 60101,
        "bonusType": 1,
        "worth": 1200
    },
    {
        "mapId": 109401,
        "location": 10,
        "posX": 6,
        "posY": 2,
        "pieceFace": 0,
        "type": 1,
        "param": 60101,
        "bonusType": 1,
        "worth": 1200
    },
    {
        "mapId": 109401,
        "location": 11,
        "posX": 5,
        "posY": 2,
        "pieceFace": 0,
        "type": 4,
        "param": 0,
        "bonusType": 5,
        "worth": 1200
    },
    {
        "mapId": 109401,
        "location": 12,
        "posX": 5,
        "posY": 3,
        "pieceFace": 0,
        "type": 1,
        "param": 60101,
        "bonusType": 1,
        "worth": 1200
    },
    {
        "mapId": 109401,
        "location": 13,
        "posX": 5,
        "posY": 4,
        "pieceFace": 0,
        "type": 1,
        "param": 60101,
        "bonusType": 1,
        "worth": 1200
    },
    {
        "mapId": 109401,
        "location": 14,
        "posX": 6,
        "posY": 4,
        "pieceFace": 0,
        "type": 1,
        "param": 60103,
        "bonusType": 2,
        "worth": 15000
    },
    {
        "mapId": 109401,
        "location": 15,
        "posX": 6,
        "posY": 5,
        "pieceFace": 0,
        "type": 1,
        "param": 60101,
        "bonusType": 1,
        "worth": 1200
    },
    {
        "mapId": 109401,
        "location": 16,
        "posX": 6,
        "posY": 6,
        "pieceFace": 0,
        "type": 3,
        "param": 0,
        "bonusType": 6,
        "worth": 1200
    },
    {
        "mapId": 109401,
        "location": 17,
        "posX": 5,
        "posY": 6,
        "pieceFace": 0,
        "type": 1,
        "param": 60101,
        "bonusType": 1,
        "worth": 1200
    },
    {
        "mapId": 109401,
        "location": 18,
        "posX": 4,
        "posY": 6,
        "pieceFace": 0,
        "type": 1,
        "param": 60101,
        "bonusType": 1,
        "worth": 1200
    },
    {
        "mapId": 109401,
        "location": 19,
        "posX": 4,
        "posY": 5,
        "pieceFace": 0,
        "type": 4,
        "param": 0,
        "bonusType": 5,
        "worth": 1200
    },
    {
        "mapId": 109401,
        "location": 20,
        "posX": 3,
        "posY": 5,
        "pieceFace": 0,
        "type": 1,
        "param": 60101,
        "bonusType": 1,
        "worth": 1200
    },
    {
        "mapId": 109401,
        "location": 21,
        "posX": 2,
        "posY": 5,
        "pieceFace": 0,
        "type": 1,
        "param": 60101,
        "bonusType": 1,
        "worth": 1200
    },
    {
        "mapId": 109401,
        "location": 22,
        "posX": 2,
        "posY": 6,
        "pieceFace": 0,
        "type": 1,
        "param": 60103,
        "bonusType": 2,
        "worth": 15000
    },
    {
        "mapId": 109401,
        "location": 23,
        "posX": 1,
        "posY": 6,
        "pieceFace": 0,
        "type": 1,
        "param": 60101,
        "bonusType": 1,
        "worth": 1200
    },
    {
        "mapId": 109401,
        "location": 24,
        "posX": 0,
        "posY": 6,
        "pieceFace": 0,
        "type": 1,
        "param": 60104,
        "bonusType": 4,
        "worth": 50000
    },
    {
        "mapId": 109401,
        "location": 25,
        "posX": 0,
        "posY": 5,
        "pieceFace": 0,
        "type": 1,
        "param": 60101,
        "bonusType": 1,
        "worth": 1200
    },
    {
        "mapId": 109401,
        "location": 26,
        "posX": 0,
        "posY": 4,
        "pieceFace": 0,
        "type": 1,
        "param": 60101,
        "bonusType": 1,
        "worth": 1200
    },
    {
        "mapId": 109401,
        "location": 27,
        "posX": 1,
        "posY": 4,
        "pieceFace": 0,
        "type": 4,
        "param": 0,
        "bonusType": 5,
        "worth": 1200
    },
    {
        "mapId": 109401,
        "location": 28,
        "posX": 1,
        "posY": 3,
        "pieceFace": 0,
        "type": 1,
        "param": 60101,
        "bonusType": 1,
        "worth": 1200
    },
    {
        "mapId": 109401,
        "location": 29,
        "posX": 1,
        "posY": 2,
        "pieceFace": 0,
        "type": 1,
        "param": 60102,
        "bonusType": 3,
        "worth": 1200
    },
    {
        "mapId": 109401,
        "location": 30,
        "posX": 0,
        "posY": 2,
        "pieceFace": 0,
        "type": 1,
        "param": 60103,
        "bonusType": 2,
        "worth": 15000
    },
    {
        "mapId": 109401,
        "location": 31,
        "posX": 0,
        "posY": 1,
        "pieceFace": 0,
        "type": 1,
        "param": 60101,
        "bonusType": 1,
        "worth": 1200
    },
    {
        "mapId": 124601,
        "location": 0,
        "posX": 0,
        "posY": 0,
        "pieceFace": 0,
        "type": 0,
        "param": 0,
        "bonusType": 0,
        "worth": 1200
    },
    {
        "mapId": 124601,
        "location": 1,
        "posX": 1,
        "posY": 0,
        "pieceFace": 0,
        "type": 1,
        "param": 60101,
        "bonusType": 1,
        "worth": 1200
    },
    {
        "mapId": 124601,
        "location": 2,
        "posX": 2,
        "posY": 0,
        "pieceFace": 0,
        "type": 1,
        "param": 60101,
        "bonusType": 1,
        "worth": 1200
    },
    {
        "mapId": 124601,
        "location": 3,
        "posX": 2,
        "posY": 1,
        "pieceFace": 0,
        "type": 4,
        "param": 0,
        "bonusType": 5,
        "worth": 1200
    },
    {
        "mapId": 124601,
        "location": 4,
        "posX": 3,
        "posY": 1,
        "pieceFace": 0,
        "type": 1,
        "param": 60101,
        "bonusType": 1,
        "worth": 1200
    },
    {
        "mapId": 124601,
        "location": 5,
        "posX": 4,
        "posY": 1,
        "pieceFace": 0,
        "type": 1,
        "param": 60101,
        "bonusType": 1,
        "worth": 1200
    },
    {
        "mapId": 124601,
        "location": 6,
        "posX": 4,
        "posY": 0,
        "pieceFace": 0,
        "type": 1,
        "param": 60103,
        "bonusType": 2,
        "worth": 15000
    },
    {
        "mapId": 124601,
        "location": 7,
        "posX": 5,
        "posY": 0,
        "pieceFace": 0,
        "type": 1,
        "param": 60101,
        "bonusType": 1,
        "worth": 1200
    },
    {
        "mapId": 124601,
        "location": 8,
        "posX": 6,
        "posY": 0,
        "pieceFace": 0,
        "type": 1,
        "param": 60102,
        "bonusType": 3,
        "worth": 1200
    },
    {
        "mapId": 124601,
        "location": 9,
        "posX": 6,
        "posY": 1,
        "pieceFace": 0,
        "type": 1,
        "param": 60101,
        "bonusType": 1,
        "worth": 1200
    },
    {
        "mapId": 124601,
        "location": 10,
        "posX": 6,
        "posY": 2,
        "pieceFace": 0,
        "type": 1,
        "param": 60101,
        "bonusType": 1,
        "worth": 1200
    },
    {
        "mapId": 124601,
        "location": 11,
        "posX": 5,
        "posY": 2,
        "pieceFace": 0,
        "type": 4,
        "param": 0,
        "bonusType": 5,
        "worth": 1200
    },
    {
        "mapId": 124601,
        "location": 12,
        "posX": 5,
        "posY": 3,
        "pieceFace": 0,
        "type": 1,
        "param": 60101,
        "bonusType": 1,
        "worth": 1200
    },
    {
        "mapId": 124601,
        "location": 13,
        "posX": 5,
        "posY": 4,
        "pieceFace": 0,
        "type": 1,
        "param": 60101,
        "bonusType": 1,
        "worth": 1200
    },
    {
        "mapId": 124601,
        "location": 14,
        "posX": 6,
        "posY": 4,
        "pieceFace": 0,
        "type": 1,
        "param": 60103,
        "bonusType": 2,
        "worth": 15000
    },
    {
        "mapId": 124601,
        "location": 15,
        "posX": 6,
        "posY": 5,
        "pieceFace": 0,
        "type": 1,
        "param": 60101,
        "bonusType": 1,
        "worth": 1200
    },
    {
        "mapId": 124601,
        "location": 16,
        "posX": 6,
        "posY": 6,
        "pieceFace": 0,
        "type": 3,
        "param": 0,
        "bonusType": 6,
        "worth": 1200
    },
    {
        "mapId": 124601,
        "location": 17,
        "posX": 5,
        "posY": 6,
        "pieceFace": 0,
        "type": 1,
        "param": 60101,
        "bonusType": 1,
        "worth": 1200
    },
    {
        "mapId": 124601,
        "location": 18,
        "posX": 4,
        "posY": 6,
        "pieceFace": 0,
        "type": 1,
        "param": 60101,
        "bonusType": 1,
        "worth": 1200
    },
    {
        "mapId": 124601,
        "location": 19,
        "posX": 4,
        "posY": 5,
        "pieceFace": 0,
        "type": 4,
        "param": 0,
        "bonusType": 5,
        "worth": 1200
    },
    {
        "mapId": 124601,
        "location": 20,
        "posX": 3,
        "posY": 5,
        "pieceFace": 0,
        "type": 1,
        "param": 60101,
        "bonusType": 1,
        "worth": 1200
    },
    {
        "mapId": 124601,
        "location": 21,
        "posX": 2,
        "posY": 5,
        "pieceFace": 0,
        "type": 1,
        "param": 60101,
        "bonusType": 1,
        "worth": 1200
    },
    {
        "mapId": 124601,
        "location": 22,
        "posX": 2,
        "posY": 6,
        "pieceFace": 0,
        "type": 1,
        "param": 60103,
        "bonusType": 2,
        "worth": 15000
    },
    {
        "mapId": 124601,
        "location": 23,
        "posX": 1,
        "posY": 6,
        "pieceFace": 0,
        "type": 1,
        "param": 60101,
        "bonusType": 1,
        "worth": 1200
    },
    {
        "mapId": 124601,
        "location": 24,
        "posX": 0,
        "posY": 6,
        "pieceFace": 0,
        "type": 1,
        "param": 60104,
        "bonusType": 4,
        "worth": 50000
    },
    {
        "mapId": 124601,
        "location": 25,
        "posX": 0,
        "posY": 5,
        "pieceFace": 0,
        "type": 1,
        "param": 60101,
        "bonusType": 1,
        "worth": 1200
    },
    {
        "mapId": 124601,
        "location": 26,
        "posX": 0,
        "posY": 4,
        "pieceFace": 0,
        "type": 1,
        "param": 60101,
        "bonusType": 1,
        "worth": 1200
    },
    {
        "mapId": 124601,
        "location": 27,
        "posX": 1,
        "posY": 4,
        "pieceFace": 0,
        "type": 4,
        "param": 0,
        "bonusType": 5,
        "worth": 1200
    },
    {
        "mapId": 124601,
        "location": 28,
        "posX": 1,
        "posY": 3,
        "pieceFace": 0,
        "type": 1,
        "param": 60101,
        "bonusType": 1,
        "worth": 1200
    },
    {
        "mapId": 124601,
        "location": 29,
        "posX": 1,
        "posY": 2,
        "pieceFace": 0,
        "type": 1,
        "param": 60102,
        "bonusType": 3,
        "worth": 1200
    },
    {
        "mapId": 124601,
        "location": 30,
        "posX": 0,
        "posY": 2,
        "pieceFace": 0,
        "type": 1,
        "param": 60103,
        "bonusType": 2,
        "worth": 15000
    },
    {
        "mapId": 124601,
        "location": 31,
        "posX": 0,
        "posY": 1,
        "pieceFace": 0,
        "type": 1,
        "param": 60101,
        "bonusType": 1,
        "worth": 1200
    },
    {
        "mapId": 24120101,
        "location": 0,
        "posX": 0,
        "posY": 0,
        "pieceFace": 0,
        "type": 0,
        "param": 0,
        "bonusType": 0,
        "worth": 1200
    },
    {
        "mapId": 24120101,
        "location": 1,
        "posX": 1,
        "posY": 0,
        "pieceFace": 0,
        "type": 1,
        "param": 60101,
        "bonusType": 1,
        "worth": 1200
    },
    {
        "mapId": 24120101,
        "location": 2,
        "posX": 2,
        "posY": 0,
        "pieceFace": 0,
        "type": 1,
        "param": 60101,
        "bonusType": 1,
        "worth": 1200
    },
    {
        "mapId": 24120101,
        "location": 3,
        "posX": 2,
        "posY": 1,
        "pieceFace": 0,
        "type": 4,
        "param": 0,
        "bonusType": 5,
        "worth": 1200
    },
    {
        "mapId": 24120101,
        "location": 4,
        "posX": 3,
        "posY": 1,
        "pieceFace": 0,
        "type": 1,
        "param": 60101,
        "bonusType": 1,
        "worth": 1200
    },
    {
        "mapId": 24120101,
        "location": 5,
        "posX": 4,
        "posY": 1,
        "pieceFace": 0,
        "type": 1,
        "param": 60101,
        "bonusType": 1,
        "worth": 1200
    },
    {
        "mapId": 24120101,
        "location": 6,
        "posX": 4,
        "posY": 0,
        "pieceFace": 0,
        "type": 1,
        "param": 60103,
        "bonusType": 2,
        "worth": 15000
    },
    {
        "mapId": 24120101,
        "location": 7,
        "posX": 5,
        "posY": 0,
        "pieceFace": 0,
        "type": 1,
        "param": 60101,
        "bonusType": 1,
        "worth": 1200
    },
    {
        "mapId": 24120101,
        "location": 8,
        "posX": 6,
        "posY": 0,
        "pieceFace": 0,
        "type": 1,
        "param": 60102,
        "bonusType": 3,
        "worth": 1200
    },
    {
        "mapId": 24120101,
        "location": 9,
        "posX": 6,
        "posY": 1,
        "pieceFace": 0,
        "type": 1,
        "param": 60101,
        "bonusType": 1,
        "worth": 1200
    },
    {
        "mapId": 24120101,
        "location": 10,
        "posX": 6,
        "posY": 2,
        "pieceFace": 0,
        "type": 1,
        "param": 60101,
        "bonusType": 1,
        "worth": 1200
    },
    {
        "mapId": 24120101,
        "location": 11,
        "posX": 5,
        "posY": 2,
        "pieceFace": 0,
        "type": 4,
        "param": 0,
        "bonusType": 5,
        "worth": 1200
    },
    {
        "mapId": 24120101,
        "location": 12,
        "posX": 5,
        "posY": 3,
        "pieceFace": 0,
        "type": 1,
        "param": 60101,
        "bonusType": 1,
        "worth": 1200
    },
    {
        "mapId": 24120101,
        "location": 13,
        "posX": 5,
        "posY": 4,
        "pieceFace": 0,
        "type": 1,
        "param": 60101,
        "bonusType": 1,
        "worth": 1200
    },
    {
        "mapId": 24120101,
        "location": 14,
        "posX": 6,
        "posY": 4,
        "pieceFace": 0,
        "type": 1,
        "param": 60103,
        "bonusType": 2,
        "worth": 15000
    },
    {
        "mapId": 24120101,
        "location": 15,
        "posX": 6,
        "posY": 5,
        "pieceFace": 0,
        "type": 1,
        "param": 60101,
        "bonusType": 1,
        "worth": 1200
    },
    {
        "mapId": 24120101,
        "location": 16,
        "posX": 6,
        "posY": 6,
        "pieceFace": 0,
        "type": 3,
        "param": 0,
        "bonusType": 6,
        "worth": 1200
    },
    {
        "mapId": 24120101,
        "location": 17,
        "posX": 5,
        "posY": 6,
        "pieceFace": 0,
        "type": 1,
        "param": 60101,
        "bonusType": 1,
        "worth": 1200
    },
    {
        "mapId": 24120101,
        "location": 18,
        "posX": 4,
        "posY": 6,
        "pieceFace": 0,
        "type": 1,
        "param": 60101,
        "bonusType": 1,
        "worth": 1200
    },
    {
        "mapId": 24120101,
        "location": 19,
        "posX": 4,
        "posY": 5,
        "pieceFace": 0,
        "type": 4,
        "param": 0,
        "bonusType": 5,
        "worth": 1200
    },
    {
        "mapId": 24120101,
        "location": 20,
        "posX": 3,
        "posY": 5,
        "pieceFace": 0,
        "type": 1,
        "param": 60101,
        "bonusType": 1,
        "worth": 1200
    },
    {
        "mapId": 24120101,
        "location": 21,
        "posX": 2,
        "posY": 5,
        "pieceFace": 0,
        "type": 1,
        "param": 60101,
        "bonusType": 1,
        "worth": 1200
    },
    {
        "mapId": 24120101,
        "location": 22,
        "posX": 2,
        "posY": 6,
        "pieceFace": 0,
        "type": 1,
        "param": 60103,
        "bonusType": 2,
        "worth": 15000
    },
    {
        "mapId": 24120101,
        "location": 23,
        "posX": 1,
        "posY": 6,
        "pieceFace": 0,
        "type": 1,
        "param": 60101,
        "bonusType": 1,
        "worth": 1200
    },
    {
        "mapId": 24120101,
        "location": 24,
        "posX": 0,
        "posY": 6,
        "pieceFace": 0,
        "type": 1,
        "param": 60104,
        "bonusType": 4,
        "worth": 50000
    },
    {
        "mapId": 24120101,
        "location": 25,
        "posX": 0,
        "posY": 5,
        "pieceFace": 0,
        "type": 1,
        "param": 60101,
        "bonusType": 1,
        "worth": 1200
    },
    {
        "mapId": 24120101,
        "location": 26,
        "posX": 0,
        "posY": 4,
        "pieceFace": 0,
        "type": 1,
        "param": 60101,
        "bonusType": 1,
        "worth": 1200
    },
    {
        "mapId": 24120101,
        "location": 27,
        "posX": 1,
        "posY": 4,
        "pieceFace": 0,
        "type": 4,
        "param": 0,
        "bonusType": 5,
        "worth": 1200
    },
    {
        "mapId": 24120101,
        "location": 28,
        "posX": 1,
        "posY": 3,
        "pieceFace": 0,
        "type": 1,
        "param": 60101,
        "bonusType": 1,
        "worth": 1200
    },
    {
        "mapId": 24120101,
        "location": 29,
        "posX": 1,
        "posY": 2,
        "pieceFace": 0,
        "type": 1,
        "param": 60102,
        "bonusType": 3,
        "worth": 1200
    },
    {
        "mapId": 24120101,
        "location": 30,
        "posX": 0,
        "posY": 2,
        "pieceFace": 0,
        "type": 1,
        "param": 60103,
        "bonusType": 2,
        "worth": 15000
    },
    {
        "mapId": 24120101,
        "location": 31,
        "posX": 0,
        "posY": 1,
        "pieceFace": 0,
        "type": 1,
        "param": 60101,
        "bonusType": 1,
        "worth": 1200
    }
]